MANIFEST.in
README.md
setup.py
src/vdk/plugin/trino/ingest_to_trino.py
src/vdk/plugin/trino/lineage_utils.py
src/vdk/plugin/trino/trino_config.py
src/vdk/plugin/trino/trino_connection.py
src/vdk/plugin/trino/trino_plugin.py
src/vdk/plugin/trino/trino_utils.py
src/vdk/plugin/trino/templates/load/dimension/scd1/00-verify-valid-target.py
src/vdk/plugin/trino/templates/load/dimension/scd1/01-test-if-view-matches-target.sql
src/vdk/plugin/trino/templates/load/dimension/scd1/02-drop-tmp-target.sql
src/vdk/plugin/trino/templates/load/dimension/scd1/03-drop-backup-target.sql
src/vdk/plugin/trino/templates/load/dimension/scd1/04-create-tmp-target.sql
src/vdk/plugin/trino/templates/load/dimension/scd1/05-insert-into-tmp-target.sql
src/vdk/plugin/trino/templates/load/dimension/scd1/06-move-data-from-tmp-to-target.py
src/vdk/plugin/trino/templates/load/dimension/scd1/README.md
src/vdk/plugin/trino/templates/load/dimension/scd2/00-verify-valid-target.py
src/vdk/plugin/trino/templates/load/dimension/scd2/01-add-props-for-args.py
src/vdk/plugin/trino/templates/load/dimension/scd2/02-test-if-view-matches-target.sql
src/vdk/plugin/trino/templates/load/dimension/scd2/03-drop-tmp-target.sql
src/vdk/plugin/trino/templates/load/dimension/scd2/04-drop-backup-target.sql
src/vdk/plugin/trino/templates/load/dimension/scd2/05-create-tmp-target.sql
src/vdk/plugin/trino/templates/load/dimension/scd2/06-insert-into-tmp-target.sql
src/vdk/plugin/trino/templates/load/dimension/scd2/07-move-data-from-tmp-to-target.py.py
src/vdk/plugin/trino/templates/load/dimension/scd2/README.md
src/vdk/plugin/trino/templates/load/fact/periodic_snapshot/00-verify-valid-target.py
src/vdk/plugin/trino/templates/load/fact/periodic_snapshot/01-test-if-view-matches-target.sql
src/vdk/plugin/trino/templates/load/fact/periodic_snapshot/02-drop-tmp-target.sql
src/vdk/plugin/trino/templates/load/fact/periodic_snapshot/03-drop-backup-target.sql
src/vdk_trino.egg-info/PKG-INFO
src/vdk_trino.egg-info/SOURCES.txt
src/vdk_trino.egg-info/dependency_links.txt
src/vdk_trino.egg-info/entry_points.txt
src/vdk_trino.egg-info/requires.txt
src/vdk_trino.egg-info/top_level.txt
